README.md
setup.cfg
setup.py
http_log.egg-info/PKG-INFO
http_log.egg-info/SOURCES.txt
http_log.egg-info/dependency_links.txt
http_log.egg-info/top_level.txt
httplog/__init__.py
httplog/log.py
httplog/patcher.py
httplog/settings.py
httplog/support/__init__.py
httplog/support/httplib2.py
httplog/support/requests.py
httplog/support/urllib2.py