Metadata-Version: 1.1
Name: http-log
Version: 2.2
Summary: httplog
Home-page: https://github.com/ifooth/httplog
Author: Joe Lei
Author-email: thezero12@hotmail.com
License: Tencent license
Keywords: httplog
Platform: UNKNOWN
Classifier: Programming Language :: Python
Classifier: Programming Language :: Python :: 2
Classifier: Programming Language :: Python :: 2.7
Classifier: Topic :: Software Development :: Libraries :: Python Modules
